<?xml version="1.0" encoding="UTF-8"?>
<collation>
    <div type="poem" corresp="#A9B99">
        <l n="1">
            <app>
                <rdg wit="#A">Se cuita grande de pesar</rdg>
                <rdg wit="#B">De coyta grande pesar</rdg>
            </app>
        </l>
        <l n="2">
            <app>
                <rdg wit="#A">non a oi' o meu coraçon</rdg>
                <rdg wit="#B">non a oi' o meu coraçon</rdg>
            </app>
        </l>
        <l n="3">
            <app>
                <rdg wit="#A">nulla mingua si deus m' anpar</rdg>
                <rdg wit="#B">nulla mingua si de<ex>us</ex> m' anpar</rdg>
            </app>
        </l>
        <l n="4">
            <app>
                <rdg wit="#A">e uedes sennor por que non</rdg>
                <rdg wit="#B">e uedes senhor por que non</rdg>
            </app>
        </l>
        <l n="5">
            <app>
                <rdg wit="#A">por que uus ueio en mi p<ex>er</ex> der</rdg>
                <rdg wit="#B">por que u<ex>os</ex> uj eu mj perder</rdg>
            </app>
        </l>
        <l n="6">
            <app>
                <rdg wit="#A">mesura que tanto ualer</rdg>
                <rdg wit="#B">mesura que tanto ualer</rdg>
            </app>
        </l>
        <l n="7">
            <app>
                <rdg wit="#A">sol sempre a quenna deus quer dar</rdg>
                <rdg wit="#B">sol sempra quena de<ex>us</ex> quer dar</rdg>
            </app>
        </l>
        <l n="8">
            <app>
                <rdg wit="#A">E se<ex>n</ex>nor mais uus direi. en</rdg>
                <rdg wit="#B">E senhor mays u<ex>os</ex> direy en</rdg>
            </app>
        </l>
        <l n="9">
            <app>
                <rdg wit="#A">esso pouco que eu poder</rdg>
                <rdg wit="#B">esso pouco q<ex>ue</ex> eu poder</rdg>
            </app>
        </l>
        <l n="10">
            <app>
                <rdg wit="#A">uiuer no mu<ex>n</ex>do se q<ex>u</ex>iser</rdg>
                <rdg wit="#B">uiu<ex>er</ex> no mu<ex>n</ex>do se q<ex>ui</ex>s<ex>er</ex></rdg>
            </app>
        </l>
        <l n="11">
            <app>
                <rdg wit="#A">deus. assi uiuerei por en</rdg>
                <rdg wit="#B">d<ex>eu</ex>s assy uiuerey p<ex>or</ex> en</rdg>
            </app>
        </l>
        <l n="12">
            <app>
                <rdg wit="#A">e ta mal dia eu naçi</rdg>
                <rdg wit="#B">eta<ex>n</ex> mal dia eu nai</rdg>
            </app>
        </l>
        <l n="13">
            <app>
                <rdg wit="#A">por q<ex>ue</ex> u<ex>os</ex> fazedes por mi</rdg>
                <rdg wit="#B">p<ex>or</ex> q<ex>ue</ex> uos fazedes p<ex>or</ex>mj</rdg>
            </app>
        </l>
        <l n="14">
            <app>
                <rdg wit="#A">cousa q<ex>ue</ex> uus no<ex>n</ex> esta ben</rdg>
                <rdg wit="#B">cousa q<ex>ue</ex>u<ex>os</ex> no<ex>n</ex> esta ben</rdg>
            </app>
        </l>
        <l n="15">
            <app>
                <rdg wit="#A">E creo q<ex>ue</ex> fara mal sen</rdg>
                <rdg wit="#B">E creo q<ex>ue</ex> fara mal sen</rdg>
            </app>
        </l>
        <l n="16">
            <app>
                <rdg wit="#A">q<ex>ue</ex>n nunca gran fiuz ouuer</rdg>
                <rdg wit="#B">q<ex>ue</ex> nu<ex>n</ex>ca g<ex>ra</ex>m feuza ouu<ex>er</ex></rdg>
            </app>
        </l>
        <l n="17">
            <app>
                <rdg wit="#A">en mesura dout* moller</rdg>
                <rdg wit="#B">en mesura dout<ex>ra</ex> molh<ex>er</ex></rdg>
            </app>
        </l>
        <l n="18">
            <app>
                <rdg wit="#A">edirei u<ex>os</ex> por q<ex>ue</ex> mia uen</rdg>
                <rdg wit="#B">edireyu<ex>os</ex> p<ex>or</ex> q<ex>ue</ex>maue<ex>n</ex></rdg>
            </app>
        </l>
        <l n="19">
            <app>
                <rdg wit="#A">por q<ex>ue</ex> me leixades assi</rdg>
                <rdg wit="#B">p<ex>or</ex> q<ex>ue</ex> me leixades assy</rdg>
            </app>
        </l>
        <l n="20">
            <app>
                <rdg wit="#A">morreR e no<ex>n</ex> catades y</rdg>
                <rdg wit="#B">morrer eno<ex>n</ex> catades hi</rdg>
            </app>
        </l>
        <l n="21">
            <app>
                <rdg wit="#A">mesura ne<ex>n</ex> d<ex>eu</ex>s ne<ex>n</ex> al ren</rdg>
                <rdg wit="#B">mesura ne<ex>n</ex> d<ex>eu</ex>s ne al ren</rdg>
            </app>
        </l>
        <l n="22">
            <app>
                <rdg wit="#A">E mia se<ex>n</ex>nor a meu cuidar</rdg>
                <rdg wit="#B">E mha senh<ex>or</ex> ameu cuydar</rdg>
            </app>
        </l>
        <l n="23">
            <app>
                <rdg wit="#A">cousa faria sen razon</rdg>
                <rdg wit="#B">cousa faria se<ex>n</ex> razo<ex>n</ex></rdg>
            </app>
        </l>
        <l n="24">
            <app>
                <rdg wit="#A">eu se miassi fuesse cuitar</rdg>
                <rdg wit="#B">eu semassy fosse matar</rdg>
            </app>
        </l>
        <l n="25">
            <app>
                <rdg wit="#A">co<ex>n</ex> mia mort enesta sazon</rdg>
                <rdg wit="#B">ca mha morte en esta sazo<ex>n</ex></rdg>
            </app>
        </l>
        <l n="26">
            <app>
                <rdg wit="#A">q<ex>ue</ex> me uos fazedes morreR</rdg>
                <rdg wit="#B">q<ex>ue</ex>me uos fazedes morrer</rdg>
            </app>
        </l>
        <l n="27">
            <app>
                <rdg wit="#A">se podess' en guissa seer</rdg>
                <rdg wit="#B">se podessen g<ex>ui</ex>sa seer</rdg>
            </app>
        </l>
        <l n="28">
            <app>
                <rdg wit="#A">q<ex>ue</ex> mal no<ex>n</ex> u<ex>os</ex> podesse estar</rdg>
                <rdg wit="#B">q<ex>ue</ex> mal no<ex>n</ex>u<ex>os</ex> podessestar</rdg>
            </app>
        </l>
    </div>
    <div type="poem" corresp="#A15B108">
        <l n="1">
            <app>
                <rdg wit="#A">De quant' eu sempre deseiei</rdg>
                <rdg wit="#B">De quant' eu sempre deseley</rdg>
            </app>
        </l>
        <l n="2">
            <app>
                <rdg wit="#A">de mia se<ex>n</ex>nor non end' ei ren</rdg>
                <rdg wit="#B">de mha senhor non end' ey re<ex>n</ex></rdg>
            </app>
        </l>
        <l n="3">
            <app>
                <rdg wit="#A">e o que muito re<del>cey</del></rdg>
                <rdg wit="#B">e o que muyto receei</rdg>
            </app>
        </l>
        <l n="4">
            <app>
                <rdg wit="#A">de mia ui<ex>n</ex>jr todo mi auen</rdg>
                <rdg wit="#B">de mha uijr todo m' auen</rdg>
            </app>
        </l>
        <l n="5">
            <app>
                <rdg wit="#A">ca sempr' eu deseiei mais d' al</rdg>
                <rdg wit="#B">ca sempr' eu deseiey mays d' al</rdg>
            </app>
        </l>
        <l n="6">
            <app>
                <rdg wit="#A">
                    <gap reason="unknown"/>
                </rdg>
                <rdg wit="#B">de uiuer con ela e mal</rdg>
            </app>
        </l>
        <l n="7">
            <app>
                <rdg wit="#A">que me pes a partir m' ey en</rdg>
                <rdg wit="#B">que me pes a partir m' ei en</rdg>
            </app>
        </l>
        <l n="8">
            <app>
                <rdg wit="#A">
                    <hi rend="guide">E</hi> ia que m' end a partir ei</rdg>
                <rdg wit="#B">E ia q<ex>ue</ex> m' e<ex>n</ex>d' a partir ey</rdg>
            </app>
        </l>
        <l n="9">
            <app>
                <rdg wit="#A">esto podela ueer ben</rdg>
                <rdg wit="#B">esto podela ueer be<ex>n</ex></rdg>
            </app>
        </l>
        <l n="10">
            <app>
                <rdg wit="#A">q<ex>ue</ex> muita guerra lle farei</rdg>
                <rdg wit="#B">q<ex>ue</ex> muyta guerra lhi farey</rdg>
            </app>
        </l>
        <l n="11">
            <app>
                <rdg wit="#A">por q<ex>ue</ex> me faz p<ex>ar</ex>tir daq<ex>ue</ex>n</rdg>
                <rdg wit="#B">p<ex>or</ex> q<ex>ue</ex> me faz p<ex>ar</ex>tir daq<ex>uen</ex></rdg>
            </app>
        </l>
        <l n="12">
            <app>
                <rdg wit="#A">ond' eu so<ex>n</ex>o mui natural</rdg>
                <rdg wit="#B">ond' eu so<ex>n</ex>o muy nat<ex>ur</ex>al</rdg>
            </app>
        </l>
        <l n="13">
            <app>
                <rdg wit="#A">e-sei ll' eu un seu ome atal</rdg>
                <rdg wit="#B">esse lhi hu<ex>n</ex> seu hom<ex>e</ex> atal</rdg>
            </app>
        </l>
        <l n="14">
            <app>
                <rdg wit="#A">q<ex>ue</ex> ll' auera morrer por en</rdg>
                <rdg wit="#B">q<ex>ue</ex> lh' aia a morrer p<ex>or</ex> en</rdg>
            </app>
        </l>
        <l n="15">
            <app>
                <rdg wit="#A">E nono pode defender</rdg>
                <rdg wit="#B">Nono pode defender</rdg>
            </app>
        </l>
        <l n="16">
            <app>
                <rdg wit="#A">de morte se mi mal fez<ex>er</ex>
                </rdg>
                <rdg wit="#B">de morte se mj mal fez<ex>er</ex></rdg>
            </app>
        </l>
        <l n="17">
            <app>
                <rdg wit="#A">ca ua<ex>n</ex> morte ei eu dauer</rdg>
                <rdg wit="#B">ca hu<ex>n</ex>a mortey eu dauer</rdg>
            </app>
        </l>
        <l n="18">
            <app>
                <rdg wit="#A">e pois eu a morrer ouuer</rdg>
                <rdg wit="#B">poys eu demorrer oer</rdg>
            </app>
        </l>
        <l n="19">
            <app>
                <rdg wit="#A">toda uia pe<ex>n</ex>nor querey</rdg>
                <rdg wit="#B">toda uya penh<ex>or</ex> q<ex>ue</ex>rrey</rdg>
            </app>
        </l>
        <l n="20">
            <app>
                <rdg wit="#A">fillar por mi e tollerlley</rdg>
                <rdg wit="#B">p<ex>or</ex>mj filhar e tolh<ex>er</ex>ey</rdg>
            </app>
        </l>
        <l n="21">
            <app>
                <rdg wit="#A">est ome por q<ex>ue</ex> me mal q<ex>ue</ex>r</rdg>
                <rdg wit="#B">est' om<ex>e</ex> p<ex>or</ex> q<ex>ue</ex> mj mal q<ex>ue</ex>r</rdg>
            </app>
        </l>
        <l n="22">
            <app>
                <rdg wit="#A">
                    <hi rend="guide">E</hi> pois ll' eu est' ome toller</rdg>
                <rdg wit="#B">E pois lh' eu est' om<ex>e</ex> tolh<ex>er</ex></rdg>
            </app>
        </l>
        <l n="23">
            <app>
                <rdg wit="#A">faça m' ela mal se poder</rdg>
                <rdg wit="#B">faça m' ela mal se poder</rdg>
            </app>
        </l>
        <l n="24">
            <app>
                <rdg wit="#A">enono podera fazer</rdg>
                <rdg wit="#B">enono pod<ex>ex</ex>a faz<ex>er</ex></rdg>
            </app>
        </l>
        <l n="25">
            <app>
                <rdg wit="#A">mais pod' ente<ex>n</ex>der se quiser</rdg>
                <rdg wit="#B">mays pod' e<ex>n</ex>tender se q<ex>ui</ex>s<ex>er</ex></rdg>
            </app>
        </l>
        <l n="26">
            <app>
                <rdg wit="#A">q<ex>ue</ex> log' eu g<ex>ua</ex>rdado serei</rdg>
                <rdg wit="#B">q<ex>ue</ex> logu' eu g<ex>uar</ex>dado s<ex>er</ex>ei</rdg>
            </app>
        </l>
        <l n="27">
            <app>
                <rdg wit="#A">
                    <ex>e</ex>
                    <am>t</am> nona temerei</rdg>
                <rdg wit="#B">dela enona tem<ex>er</ex>ey</rdg>
            </app>
        </l>
        <l n="28">
            <app>
                <rdg wit="#A">desquell' eu esto feit ouuer</rdg>
                <rdg wit="#B">desq<ex>ue</ex>lh' este penh<ex>or</ex> p<ex>or</ex>ser</rdg>
            </app>
        </l>
    </div>
</collation>
